{
  
    "store": [
        {
            "name": "Basic Sword",
            "price": 7,
            "power": 2
        },
        {
            "name": "Apple",
            "price": 3,
            "health": 5
        },
        {
            "name": "Potion",
            "price": 10,
            "health": 20
        },
        {
            "name": "Spear",
            "price": 35,
            "power": 10
        },
        {
            "name": "Chailmail",
            "price": 50,
            "armor": 5
        }
    ],
    "rooms": [
        {
            "id": 1,
            "desc": "a somewhat smaller room",
            "north": 3,
            "south": 2,
            "east": 8,
            "west": 1
        },
        {
            "id": 2,
            "desc": "a somewhat smaller room",
            "north": null,
            "south": null,
            "east": 8,
            "west": 1
        },
        {
            "id": 3,
            "desc": "The escape room",
            "north": null,
            "south": 1,
            "east": null,
            "west": null,
            "requires_key": "Master Key",
            "winner": true
        },
        {
            "id": 4,
            "desc": "a small room, it looks like the walls are closing in!",
            "north": 1,
            "south": 6,
            "east": 5,
            "west": 7
        },
        {
            "id": 5,
            "desc": "a room with vines and grass",
            "north": null,
            "south": null,
            "east": null,
            "west": 4
        },
        {
            "id": 6,
            "desc": "the tresure room",
            "north": 4,
            "south": null,
            "east": null,
            "west": null
        },
        {
            "id": 7,
            "desc": "a large room with dust and skeletons",
            "north": null,
            "south": null,
            "east": 4,
            "west": null
        },
        {
            "id": 8,
            "desc": "a dead end",
            "north": null,
            "south": null,
            "east": null,
            "west": 2
        }
    ],
    "monsters": [
        {
            "name": "slime",
            "room_id": 2,
            "health": 10,
            "attack": 2,
            "starting_health": 10
        },

        {
            "name": "squirtle",
            "room_id": 3,
            "health": 20,
            "attack": 4,
            "starting_health": 20
        },

        {
            "name": "goblin",
            "room_id": 4,
            "health": 20,
            "attack": 5,
            "starting_health": 20
        },

        {
            "name": "dragon",
            "room_id": 5,
            "health": 55,
            "attack": 10,
            "starting_health": 55
        },

        {
            "name": "boss",
            "room_id": 6,
            "health": 100,
            "attack": 20,
            "starting_health": 100
        },

        {
            "name": "red thing",
            "room_id": 7,
            "health": 10,
            "attack": 4,
            "starting_health": 10
        }
    ],
    "items": [
        {
            "name": "Master Key",
            "room_id": 2
        },
        {
            "name": "Potion",
            "room_id": 5
        },
        {
            "name": "Bag of Shekels",
            "room_id": 6
        },
        {
            "name": "Treasure Chest",
            "room_id": 7
        }
    ]
}